{
  "name": "Premier Remediation 2",
  "tagline": "Advanced Trenchless Solutions & Commercial Plumbing Services",
  "description": "Premier Remediation 2 specializes in minimally invasive trenchless pipe repair and comprehensive commercial plumbing services throughout the Bay Area. We use cutting-edge CIPP technology and modern methods to restore critical infrastructure with minimal disruption to your property and operations.",
  "phone": "(650) 379-8166",
  "phoneRaw": "6503798166",
  "email": "info@westpeak.biz",
  "address": {
    "street": "1030 Duane Ave",
    "city": "Santa Clara",
    "state": "CA",
    "zip": "95054",
    "full": "1030 Duane Ave, Santa Clara, CA 95054"
  },
  "owner": "Juan",
  "logo": "/logo.png",
  "colors": {
    "primary": "#1B365D",
    "secondary": "#4A90A4",
    "accent": "#FFA500"
  },
  "hours": "24/7 Emergency Services Available",
  "certifications": [
    "CIPP Certified",
    "Licensed Plumbing Contractor"
  ],
  "uniqueSellingPoints": [
    "Advanced CIPP trenchless technology",
    "24/7 emergency response including weekends and holidays",
    "Minimally invasive pipe restoration",
    "Commercial-focused expertise",
    "High-pressure hydro jetting up to 4,000 PSI",
    "Video camera inspection capabilities"
  ],
  "social": {},
  "seo": {
    "metaTitle": "Premier Remediation 2 - Trenchless Pipe Repair & Commercial Plumbing | Bay Area",
    "metaDescription": "Expert trenchless pipe repair and commercial plumbing services in the Bay Area. CIPP lining, hydro jetting, emergency sewer repair. 24/7 service available."
  }
}